mockTestIC/__init__.py
mockTestIC/mockTestIC.py
mockTestIC-3.0.12.dist-info/LICENSE
mockTestIC-3.0.12.dist-info/METADATA
mockTestIC-3.0.12.dist-info/WHEEL
mockTestIC-3.0.12.dist-info/top_level.txt
mockTestIC-3.0.12.dist-info/RECORD
