Metadata-Version: 2.1
Name: mockTestIC
Version: 3.0.12
Summary: Este projeto é uma biblioteca Python chamada mockTestIC que utiliza a biblioteca Faker para gerar dados fictícios com base em um mapeamento pré-definido.
Author: Victor Augusto do Carmo
Author-email: Victoraugustodocarmo32@gmail.com
License: MIT License
Keywords: mockTest,dados falsos,insert de dados falsos,dados ficticios,SQL,gerador de dados,false data,fictitious data,data,dados,data generator
License-File: LICENSE
Requires-Dist: pydantic
Requires-Dist: faker
Requires-Dist: typing-extensions
Requires-Dist: setuptools
